CHANGES.txt
LICENSE.txt
MANIFEST.in
README.txt
__init__.py
settings.py
setup.py
printflow2/FileSystemMonitor.py
printflow2/JDs.py
printflow2/NooshMonitor.py
printflow2/PdfToolbox.py
printflow2/WorkflowManager.py
printflow2/__init__.py
printflow2/callas_testing.py
printflow2/categorybuilder.py
printflow2/main.py
printflow2/main_damreport.py
printflow2/nooshsoap.py
printflow2/utils.py
pyprintflow2.egg-info/PKG-INFO
pyprintflow2.egg-info/SOURCES.txt
pyprintflow2.egg-info/dependency_links.txt
pyprintflow2.egg-info/entry_points.txt
pyprintflow2.egg-info/requires.txt
pyprintflow2.egg-info/top_level.txt