Metadata-Version: 1.1
Name: pyprintflow2
Version: 2.5.10
Summary: Manage integration of Noosh and Cumulus to provide integrated print project management
Home-page: http://printflow2.com/pyprintflow2service
Author: Colin Manning
Author-email: colin@printoutsource.com
License: GPL
Keywords: print dam cumulus noosh
Platform: UNKNOWN
Classifier: Development Status :: 5 - Production/Stable
Classifier: Topic :: Utilities
Classifier: License :: Free for non-commercial use
Classifier: Intended Audience :: Information Technology
Classifier: Programming Language :: Python :: 3.3
